hallu_assess-0.1.0.dist-info/licenses/LICENSE
halluassess/__init__.py
halluassess/errors.py
halluassess/evaluate.py
halluassess/results.py
halluassess/embeddings/encoder.py
halluassess/llms/factory.py
halluassess/prompts/builder.py
halluassess/sampling/runner.py
halluassess/scoring/similarity.py
hallu_assess-0.1.0.dist-info/METADATA
hallu_assess-0.1.0.dist-info/WHEEL
hallu_assess-0.1.0.dist-info/top_level.txt
hallu_assess-0.1.0.dist-info/RECORD
