Metadata-Version: 2.4
Name: hallu-assess
Version: 0.1.0
Summary: Measure how much an LLM’s answers drift to detect hallucination risk and improve prompts for more reliable results.
Author: Ashwin B
License-Expression: MIT
Project-URL: Homepage, https://github.com/ashley1902/hallu-assess
Project-URL: Repository, https://github.com/ashley1902/hallu-assess
Project-URL: Issues, https://github.com/ashley1902/hallu-assess/issues
Requires-Python: >=3.9
License-File: LICENSE
Requires-Dist: numpy
Requires-Dist: sentence-transformers
Requires-Dist: langchain-core
Requires-Dist: langchain-openai
Requires-Dist: langchain-google-genai
Requires-Dist: langchain-anthropic
Dynamic: license-file
